raptacon3200/__init__.py
raptacon3200/bot_factory/botFactory.py
raptacon3200/bot_factory/hardwareFactory.py
raptacon3200/bot_factory/sensorFactory.py
raptacon3200/config/configMapper.py
raptacon3200/constants/common.py
raptacon3200/utils/botFinder.py
raptacon3200/utils/leds.py
raptacon3200/utils/motorHelper.py
raptacon3200/utils/sparkMaxUtils.py
raptacon3200/utils/test_leds.py
raptacon3200/utils/unit_enums.py
raptacon3200/yaml/README.md
raptacon3200/yaml/__init__.py
raptacon3200/yaml/composer.py
raptacon3200/yaml/constructor.py
raptacon3200/yaml/cyaml.py
raptacon3200/yaml/dumper.py
raptacon3200/yaml/emitter.py
raptacon3200/yaml/error.py
raptacon3200/yaml/events.py
raptacon3200/yaml/loader.py
raptacon3200/yaml/nodes.py
raptacon3200/yaml/parser.py
raptacon3200/yaml/reader.py
raptacon3200/yaml/representer.py
raptacon3200/yaml/resolver.py
raptacon3200/yaml/scanner.py
raptacon3200/yaml/serializer.py
raptacon3200/yaml/tokens.py
raptacon3200-2025.2.5.dist-info/LICENSE
raptacon3200-2025.2.5.dist-info/METADATA
raptacon3200-2025.2.5.dist-info/WHEEL
raptacon3200-2025.2.5.dist-info/RECORD
