Metadata-Version: 2.3
Name: raptacon3200
Version: 2025.2.5
Summary: A FRC Raptacon 3200 Robot Common Library
Author: Nathan Beasley
Author-email: nathan@example.com
Requires-Python: >= 3.12
Classifier: Programming Language :: Python :: 3
Classifier: License :: OSI Approved :: MIT License
Classifier: Operating System :: OS Independent
Classifier: Programming Language :: Python :: 3.12
Classifier: Development Status :: 3 - Alpha
Requires-Dist: robotpy-rev (>=2025.0.2,<2026.0.0)
Project-URL: Bug Tracker, https://github.com/raptacon/raptacon3200/issues
Project-URL: Homepage, https://github.com/raptacon/raptacon3200
